Workbook

Sheet Parametros
A1: Parametro | B1: Valor | C1: Descripcion
A2: Anio | B2: 2026 | C2: Ano fiscal editable
A3: Mes | B3: 5 | C3: Mes de liquidacion 1-12
A4: DiasPeriodo | B4: 30 | C4: Dias liquidados por periodo
A5: SMLMV | B5: 1750905 | C5: Salario minimo legal mensual vigente 2026
A6: AuxTransporte | B6: 249095 | C6: Auxilio legal de transporte mensual 2026
A7: TopeAuxTransporte | B7: 3501810 | C7: Aplica si salario base <= 2 SMLMV
A8: HorasMes | B8: 240 | C8: Base de horas mensuales para valor hora
A9: SaludEmpleado | B9: 0.04 | C9: Aporte salud empleado
A10: PensionEmpleado | B10: 0.04 | C10: Aporte pension empleado
A11: RiesgoValidacionSalarioAlto | B11: 20000000 | C11: Umbral de alerta por salario alto
A12: FactorHoraExtraDiurna | B12: 1.25 | C12: Factor sobre hora ordinaria
A13: FactorHoraExtraNocturna | B13: 1.75 | C13: Factor sobre hora ordinaria
... A15: FactorDominicalFestivo | B15: 1.75 | C15: Factor sobre hora ordinaria
A16: FuenteSMLMV | B16: Decreto 1469 de 2025 / Presidencia Colombia | C16: Referencia normativa cargada en mayo de 2026
A17: FuenteAuxTransporte | B17: Decreto 1470 de 2025 / SUIN Juriscol | C17: Referencia normativa cargada en mayo de 2026

Sheet Empleados
A1: ID | B1: Nombre | C1: Cargo | D1: Area | E1: SalarioBase | F1: TipoContrato | G1: HorasContratadas | H1: FechaIngreso | I1: EPS | J1: Pension | K1: Ciudad | L1: Activo | M1: ObservacionAgente
A2: EMP-0001 | B2: Paula Torres | C2: Desarrollador Senior | D2: Finanzas | E2: 1750905 | F2: Fijo | G2: 240 | H2: 44875 | I2: Sanitas | J2: Proteccion | K2: Barranquilla | L2: Si
A3: EMP-0002 | B3: Sofia Rodriguez | C3: Analista de Nomina | D3: Operaciones | E3: 1750905 | F3: Fijo | G3: 240 | H3: 43554 | I3: Nueva EPS | J3: Skandia | K3: Bogota | L3: Si
A4: EMP-0003 | B4: Jorge Garcia | C4: Jefe de Talento Humano | D4: Comercial | E4: 1750905 | F4: Fijo | G4: 240 | H4: 45289 | I4: Compensar | J4: Colfondos | K4: Cali | L4: Si
A5: EMP-0004 | B5: Ana Jimenez | C5: Asistente Administrativo | D5: Finanzas | E5: 1750905 | F5: Indefinido | G5: 240 | H5: 45971 | I5: Compensar | J5: Colfondos | K5: Cali | L5: Si
A6: EMP-0005 | B6: David Moreno | C6: Desarrollador Junior | D6: Operaciones | E6: 1750905 | F6: Fijo | G6: 240 | H6: 44106 | I6: Famisanar | J6: Proteccion | K6: Cali | L6: Si
A7: EMP-0006 | B7: Juan Sanchez | C7: Contador | D7: Tecnologia | E7: 4940000 | F7: Indefinido | G7: 240 | H7: 43663 | I7: Sura | J7: Colfondos | K7: Barranquilla | L7: Si
A8: EMP-0007 | B8: Nicolas Diaz | C8: Contador | D8: Administracion | E8: 5720000 | F8: Aprendizaje | G8: 240 | H8: 45940 | I8: Nueva EPS | J8: Colpensiones | K8: Medellin | L8: Si
A9: EMP-0008 | B9: Diego Castro | C9: Supervisor de Planta | D9: Tecnologia | E9: 3600000 | F9: Obra labor | G9: 240 | H9: 44279 | I9: Salud Total | J9: Skandia | K9: Cali | L9: Si
A10: EMP-0009 | B10: Isabella Diaz | C10: Coordinador Comercial | D10: Comercial | E10: 5400000 | F10: Indefinido | G10: 240 | H10: 45072 | I10: Salud Total | J10: Proteccion | K10: Bogota | L10: Si
A11: EMP-0010 | B11: Miguel Torres | C11: Desarrollador Junior | D11: Operaciones | E11: 3800000 | F11: Fijo | G11: 240 | H11: 45213 | I11: Compensar | J11: Colpensiones | K11: Medellin | L11: Si
A12: EMP-0011 | B12: Sebastian Diaz | C12: Vendedor | D12: Talento Humano | E12: 2185000 | F12: Fijo | G12: 240 | H12: 45733 | I12: Compensar | J12: Colfondos | K12: Cali | L12: Si
A13: EMP-0012 | B13: Paula Martinez | C13: Desarrollador Senior | D13: Talento Humano | E13: 8075000 | F13: Fijo | G13: 240 | H13: 44837 | I13: Nueva EPS | J13: Porvenir | K13: Barranquilla | L13: Si
... A31: EMP-0030 | B31: Isabella Lopez | C31: Vendedor | D31: Tecnologia | E31: 2760000 | F31: Fijo | G31: 240 | H31: 43663 | I31: Nueva EPS | J31: Porvenir | K31: Cali | L31: Si
A32: EMP-0031 | B32: Sebastian Moreno | C32: Auxiliar Operativo | D32: Operaciones | E32: 1750905 | F32: Indefinido | G32: 240 | H32: 46168 | I32: Compensar | J32: Colfondos | K32: Bogota | L32: Si | M32: Creado desde Telegram
A33: EMP-0032 | B33: Carolina Hernandez | C33: Auxiliar Operativo | D33: Operaciones | E33: 1750905 | F33: Indefinido | G33: 240 | H33: 46168 | I33: Famisanar | J33: Proteccion | K33: Bogota | L33: Si | M33: Creado desde Telegram
A34: EMP-0033 | B34: Nicolas Rodriguez | C34: Auxiliar Operativo | D34: Administracion | E34: 1750905 | F34: Indefinido | G34: 240 | H34: 46168 | I34: Famisanar | J34: Proteccion | K34: Bogota | L34: Si | M34: Creado desde Telegram
A35: EMP-0034 | B35: Nicolas Perez | C35: Auxiliar Operativo | D35: Finanzas | E35: 1750905 | F35: Indefinido | G35: 240 | H35: 46168 | I35: Salud Total | J35: Colpensiones | K35: Bogota | L35: Si | M35: Creado desde Telegram
A36: EMP-0035 | B36: Andres Moreno | C36: Auxiliar Operativo | D36: Operaciones | E36: 1750905 | F36: Indefinido | G36: 240 | H36: 46168 | I36: Sanitas | J36: Proteccion | K36: Bogota | L36: Si | M36: Creado desde Telegram

Sheet Novedades_Horas
A1: ID | B1: EmpleadoID | C1: HorasOrdinarias | D1: HorasExtraDiurnas | E1: HorasExtraNocturnas | F1: HorasRecargoNocturno | G1: HorasDominicalFestivo | H1: DiasNoTrabajados | I1: Bonificaciones | J1: PrestamosDescuentos | K1: Observacion
A2: NOV-0001 | B2: EMP-0001 | C2: 224 | D2: 8 | E2: 4 | F2: 5 | G2: 8 | H2: 2 | I2: 300000 | J2: 0
A3: NOV-0002 | B3: EMP-0002 | C3: 224 | D3: 8 | E3: 4 | F3: 0 | G3: 8 | H3: 0 | I3: 150000 | J3: 250000
A4: NOV-0003 | B4: EMP-0003 | C4: 232 | D4: 0 | E4: 0 | F4: 0 | G4: 0 | H4: 0 | I4: 0 | J4: 0
A5: NOV-0004 | B5: EMP-0004 | C5: 224 | D5: 2 | E5: 4 | F5: 8 | G5: 0 | H5: 0 | I5: 0 | J5: 0
A6: NOV-0005 | B6: EMP-0005 | C6: 240 | D6: 8 | E6: 2 | F6: 5 | G6: 8 | H6: 0 | I6: 0 | J6: 0
A7: NOV-0006 | B7: EMP-0006 | C7: 240 | D7: 4 | E7: 2 | F7: 0 | G7: 0 | H7: 2 | I7: 150000 | J7: 0
A8: NOV-0007 | B8: EMP-0007 | C8: 224 | D8: 6 | E8: 1 | F8: 0 | G8: 0 | H8: 0 | I8: 500000 | J8: 0
A9: NOV-0008 | B9: EMP-0008 | C9: 240 | D9: 0 | E9: 0 | F9: 10 | G9: 0 | H9: 0 | I9: 0 | J9: 0
A10: NOV-0009 | B10: EMP-0009 | C10: 240 | D10: 0 | E10: 4 | F10: 0 | G10: 0 | H10: 0 | I10: 0 | J10: 0
A11: NOV-0010 | B11: EMP-0010 | C11: 240 | D11: 2 | E11: 2 | F11: 5 | G11: 0 | H11: 0 | I11: 500000 | J11: 100000
A12: NOV-0011 | B12: EMP-0011 | C12: 240 | D12: 0 | E12: 0 | F12: 0 | G12: 8 | H12: 2 | I12: 500000 | J12: 0
A13: NOV-0012 | B13: EMP-0012 | C13: 240 | D13: 2 | E13: 4 | F13: 5 | G13: 8 | H13: 2 | I13: 0 | J13: 0
... A31: NOV-0030 | B31: EMP-0030 | C31: 232 | D31: 6 | E31: 0 | F31: 10 | G31: 8 | H31: 0 | I31: 150000 | J31: 0
A32: NOV-0031 | B32: EMP-0031 | C32: 240 | D32: 0 | E32: 0 | F32: 0 | G32: 0 | H32: 0 | I32: 0 | J32: 0 | K32: Creado desde Telegram
A33: NOV-0032 | B33: EMP-0032 | C33: 240 | D33: 0 | E33: 0 | F33: 0 | G33: 0 | H33: 0 | I33: 0 | J33: 0 | K33: Creado desde Telegram
A34: NOV-0033 | B34: EMP-0033 | C34: 240 | D34: 0 | E34: 0 | F34: 0 | G34: 0 | H34: 0 | I34: 0 | J34: 0 | K34: Creado desde Telegram
A35: NOV-0034 | B35: EMP-0034 | C35: 240 | D35: 0 | E35: 0 | F35: 0 | G35: 0 | H35: 0 | I35: 0 | J35: 0 | K35: Creado desde Telegram
A36: NOV-0035 | B36: EMP-0035 | C36: 240 | D36: 0 | E36: 0 | F36: 0 | G36: 0 | H36: 0 | I36: 0 | J36: 0 | K36: Creado desde Telegram

Sheet Calculo_Nomina
A1: EmpleadoID | B1: Nombre | C1: Cargo | D1: Area | E1: SalarioBase | F1: ValorHora | G1: SalarioDevengado | H1: AuxTransporte | I1: ValorExtrasRecargos | J1: Bonificaciones | K1: TotalDevengado | L1: Salud | M1: Pension | N1: RetencionFuente | O1: PrestamosDescuentos | P1: TotalDeducciones | Q1: NetoAPagar | R1: CostoEmpresaEstimado | S1: EstadoAgente
A2: =Empleados!A2 | B2: =Empleados!B2 | C2: =Empleados!C2 | D2: =Empleados!D2 | E2: =Empleados!E2 | F2: =E2/Parametros!$B$8 | G2: =ROUND(E2/Parametros!$B$8*Novedades_Horas!C2,0) | H2: =IF(AND(E2<=Parametros!$B$7,Empleados!L2="Si"),Parametros!$B$6,0) | I2: =ROUND(F2*(Novedades_Horas!D2*Parametros!$B$12+Novedades_Horas!E2*Parametros!$B$13+Novedades_Horas!F2*Parametros!$B$14+Novedades_Horas!G2*Parametros!$B$15),0) | J2: =Novedades_Horas!I2 | K2: =SUM(G2:J2) | L2: =ROUND((G2+I2+J2)*Parametros!$B$9,0) | M2: =ROUND((G2+I2+J2)*Parametros!$B$10,0) | N2: =IF(K2>6000000,ROUND((K2-6000000)*0.1,0),0) | O2: =Novedades_Horas!J2 | P2: =SUM(L2:O2) | Q2: =K2-P2 | R2: =ROUND(K2+(G2+I2+J2)*0.205,0) | S2: =IF(Q2<0,"ERROR: Neto negativo",IF(E2<Parametros!$B$5,"ERROR: Salario bajo",IF(E2>Parametros!$B$11,"REVISAR: salario alto","OK")))
A3: =Empleados!A3 | B3: =Empleados!B3 | C3: =Empleados!C3 | D3: =Empleados!D3 | E3: =Empleados!E3 | F3: =E3/Parametros!$B$8 | G3: =ROUND(E3/Parametros!$B$8*Novedades_Horas!C3,0) | H3: =IF(AND(E3<=Parametros!$B$7,Empleados!L3="Si"),Parametros!$B$6,0) | I3: =ROUND(F3*(Novedades_Horas!D3*Parametros!$B$12+Novedades_Horas!E3*Parametros!$B$13+Novedades_Horas!F3*Parametros!$B$14+Novedades_Horas!G3*Parametros!$B$15),0) | J3: =Novedades_Horas!I3 | K3: =SUM(G3:J3) | L3: =ROUND((G3+I3+J3)*Parametros!$B$9,0) | M3: =ROUND((G3+I3+J3)*Parametros!$B$10,0) | N3: =IF(K3>6000000,ROUND((K3-6000000)*0.1,0),0) | O3: =Novedades_Horas!J3 | P3: =SUM(L3:O3) | Q3: =K3-P3 | R3: =ROUND(K3+(G3+I3+J3)*0.205,0) | S3: =IF(Q3<0,"ERROR: Neto negativo",IF(E3<Parametros!$B$5,"ERROR: Salario bajo",IF(E3>Parametros!$B$11,"REVISAR: salario alto","OK")))
A4: =Empleados!A4 | B4: =Empleados!B4 | C4: =Empleados!C4 | D4: =Empleados!D4 | E4: =Empleados!E4 | F4: =E4/Parametros!$B$8 | G4: =ROUND(E4/Parametros!$B$8*Novedades_Horas!C4,0) | H4: =IF(AND(E4<=Parametros!$B$7,Empleados!L4="Si"),Parametros!$B$6,0) | I4: =ROUND(F4*(Novedades_Horas!D4*Parametros!$B$12+Novedades_Horas!E4*Parametros!$B$13+Novedades_Horas!F4*Parametros!$B$14+Novedades_Horas!G4*Parametros!$B$15),0) | J4: =Novedades_Horas!I4 | K4: =SUM(G4:J4) | L4: =ROUND((G4+I4+J4)*Parametros!$B$9,0) | M4: =ROUND((G4+I4+J4)*Parametros!$B$10,0) | N4: =IF(K4>6000000,ROUND((K4-6000000)*0.1,0),0) | O4: =Novedades_Horas!J4 | P4: =SUM(L4:O4) | Q4: =K4-P4 | R4: =ROUND(K4+(G4+I4+J4)*0.205,0) | S4: =IF(Q4<0,"ERROR: Neto negativo",IF(E4<Parametros!$B$5,"ERROR: Salario bajo",IF(E4>Parametros!$B$11,"REVISAR: salario alto","OK")))
A5: =Empleados!A5 | B5: =Empleados!B5 | C5: =Empleados!C5 | D5: =Empleados!D5 | E5: =Empleados!E5 | F5: =E5/Parametros!$B$8 | G5: =ROUND(E5/Parametros!$B$8*Novedades_Horas!C5,0) | H5: =IF(AND(E5<=Parametros!$B$7,Empleados!L5="Si"),Parametros!$B$6,0) | I5: =ROUND(F5*(Novedades_Horas!D5*Parametros!$B$12+Novedades_Horas!E5*Parametros!$B$13+Novedades_Horas!F5*Parametros!$B$14+Novedades_Horas!G5*Parametros!$B$15),0) | J5: =Novedades_Horas!I5 | K5: =SUM(G5:J5) | L5: =ROUND((G5+I5+J5)*Parametros!$B$9,0) | M5: =ROUND((G5+I5+J5)*Parametros!$B$10,0) | N5: =IF(K5>6000000,ROUND((K5-6000000)*0.1,0),0) | O5: =Novedades_Horas!J5 | P5: =SUM(L5:O5) | Q5: =K5-P5 | R5: =ROUND(K5+(G5+I5+J5)*0.205,0) | S5: =IF(Q5<0,"ERROR: Neto negativo",IF(E5<Parametros!$B$5,"ERROR: Salario bajo",IF(E5>Parametros!$B$11,"REVISAR: salario alto","OK")))
A6: =Empleados!A6 | B6: =Empleados!B6 | C6: =Empleados!C6 | D6: =Empleados!D6 | E6: =Empleados!E6 | F6: =E6/Parametros!$B$8 | G6: =ROUND(E6/Parametros!$B$8*Novedades_Horas!C6,0) | H6: =IF(AND(E6<=Parametros!$B$7,Empleados!L6="Si"),Parametros!$B$6,0) | I6: =ROUND(F6*(Novedades_Horas!D6*Parametros!$B$12+Novedades_Horas!E6*Parametros!$B$13+Novedades_Horas!F6*Parametros!$B$14+Novedades_Horas!G6*Parametros!$B$15),0) | J6: =Novedades_Horas!I6 | K6: =SUM(G6:J6) | L6: =ROUND((G6+I6+J6)*Parametros!$B$9,0) | M6: =ROUND((G6+I6+J6)*Parametros!$B$10,0) | N6: =IF(K6>6000000,ROUND((K6-6000000)*0.1,0),0) | O6: =Novedades_Horas!J6 | P6: =SUM(L6:O6) | Q6: =K6-P6 | R6: =ROUND(K6+(G6+I6+J6)*0.205,0) | S6: =IF(Q6<0,"ERROR: Neto negativo",IF(E6<Parametros!$B$5,"ERROR: Salario bajo",IF(E6>Parametros!$B$11,"REVISAR: salario alto","OK")))
A7: =Empleados!A7 | B7: =Empleados!B7 | C7: =Empleados!C7 | D7: =Empleados!D7 | E7: =Empleados!E7 | F7: =E7/Parametros!$B$8 | G7: =ROUND(E7/Parametros!$B$8*Novedades_Horas!C7,0) | H7: =IF(AND(E7<=Parametros!$B$7,Empleados!L7="Si"),Parametros!$B$6,0) | I7: =ROUND(F7*(Novedades_Horas!D7*Parametros!$B$12+Novedades_Horas!E7*Parametros!$B$13+Novedades_Horas!F7*Parametros!$B$14+Novedades_Horas!G7*Parametros!$B$15),0) | J7: =Novedades_Horas!I7 | K7: =SUM(G7:J7) | L7: =ROUND((G7+I7+J7)*Parametros!$B$9,0) | M7: =ROUND((G7+I7+J7)*Parametros!$B$10,0) | N7: =IF(K7>6000000,ROUND((K7-6000000)*0.1,0),0) | O7: =Novedades_Horas!J7 | P7: =SUM(L7:O7) | Q7: =K7-P7 | R7: =ROUND(K7+(G7+I7+J7)*0.205,0) | S7: =IF(Q7<0,"ERROR: Neto negativo",IF(E7<Parametros!$B$5,"ERROR: Salario bajo",IF(E7>Parametros!$B$11,"REVISAR: salario alto","OK")))
A8: =Empleados!A8 | B8: =Empleados!B8 | C8: =Empleados!C8 | D8: =Empleados!D8 | E8: =Empleados!E8 | F8: =E8/Parametros!$B$8 | G8: =ROUND(E8/Parametros!$B$8*Novedades_Horas!C8,0) | H8: =IF(AND(E8<=Parametros!$B$7,Empleados!L8="Si"),Parametros!$B$6,0) | I8: =ROUND(F8*(Novedades_Horas!D8*Parametros!$B$12+Novedades_Horas!E8*Parametros!$B$13+Novedades_Horas!F8*Parametros!$B$14+Novedades_Horas!G8*Parametros!$B$15),0) | J8: =Novedades_Horas!I8 | K8: =SUM(G8:J8) | L8: =ROUND((G8+I8+J8)*Parametros!$B$9,0) | M8: =ROUND((G8+I8+J8)*Parametros!$B$10,0) | N8: =IF(K8>6000000,ROUND((K8-6000000)*0.1,0),0) | O8: =Novedades_Horas!J8 | P8: =SUM(L8:O8) | Q8: =K8-P8 | R8: =ROUND(K8+(G8+I8+J8)*0.205,0) | S8: =IF(Q8<0,"ERROR: Neto negativo",IF(E8<Parametros!$B$5,"ERROR: Salario bajo",IF(E8>Parametros!$B$11,"REVISAR: salario alto","OK")))
A9: =Empleados!A9 | B9: =Empleados!B9 | C9: =Empleados!C9 | D9: =Empleados!D9 | E9: =Empleados!E9 | F9: =E9/Parametros!$B$8 | G9: =ROUND(E9/Parametros!$B$8*Novedades_Horas!C9,0) | H9: =IF(AND(E9<=Parametros!$B$7,Empleados!L9="Si"),Parametros!$B$6,0) | I9: =ROUND(F9*(Novedades_Horas!D9*Parametros!$B$12+Novedades_Horas!E9*Parametros!$B$13+Novedades_Horas!F9*Parametros!$B$14+Novedades_Horas!G9*Parametros!$B$15),0) | J9: =Novedades_Horas!I9 | K9: =SUM(G9:J9) | L9: =ROUND((G9+I9+J9)*Parametros!$B$9,0) | M9: =ROUND((G9+I9+J9)*Parametros!$B$10,0) | N9: =IF(K9>6000000,ROUND((K9-6000000)*0.1,0),0) | O9: =Novedades_Horas!J9 | P9: =SUM(L9:O9) | Q9: =K9-P9 | R9: =ROUND(K9+(G9+I9+J9)*0.205,0) | S9: =IF(Q9<0,"ERROR: Neto negativo",IF(E9<Parametros!$B$5,"ERROR: Salario bajo",IF(E9>Parametros!$B$11,"REVISAR: salario alto","OK")))
A10: =Empleados!A10 | B10: =Empleados!B10 | C10: =Empleados!C10 | D10: =Empleados!D10 | E10: =Empleados!E10 | F10: =E10/Parametros!$B$8 | G10: =ROUND(E10/Parametros!$B$8*Novedades_Horas!C10,0) | H10: =IF(AND(E10<=Parametros!$B$7,Empleados!L10="Si"),Parametros!$B$6,0) | I10: =ROUND(F10*(Novedades_Horas!D10*Parametros!$B$12+Novedades_Horas!E10*Parametros!$B$13+Novedades_Horas!F10*Parametros!$B$14+Novedades_Horas!G10*Parametros!$B$15),0) | J10: =Novedades_Horas!I10 | K10: =SUM(G10:J10) | L10: =ROUND((G10+I10+J10)*Parametros!$B$9,0) | M10: =ROUND((G10+I10+J10)*Parametros!$B$10,0) | N10: =IF(K10>6000000,ROUND((K10-6000000)*0.1,0),0) | O10: =Novedades_Horas!J10 | P10: =SUM(L10:O10) | Q10: =K10-P10 | R10: =ROUND(K10+(G10+I10+J10)*0.205,0) | S10: =IF(Q10<0,"ERROR: Neto negativo",IF(E10<Parametros!$B$5,"ERROR: Salario bajo",IF(E10>Parametros!$B$11,"REVISAR: salario alto","OK")))
A11: =Empleados!A11 | B11: =Empleados!B11 | C11: =Empleados!C11 | D11: =Empleados!D11 | E11: =Empleados!E11 | F11: =E11/Parametros!$B$8 | G11: =ROUND(E11/Parametros!$B$8*Novedades_Horas!C11,0) | H11: =IF(AND(E11<=Parametros!$B$7,Empleados!L11="Si"),Parametros!$B$6,0) | I11: =ROUND(F11*(Novedades_Horas!D11*Parametros!$B$12+Novedades_Horas!E11*Parametros!$B$13+Novedades_Horas!F11*Parametros!$B$14+Novedades_Horas!G11*Parametros!$B$15),0) | J11: =Novedades_Horas!I11 | K11: =SUM(G11:J11) | L11: =ROUND((G11+I11+J11)*Parametros!$B$9,0) | M11: =ROUND((G11+I11+J11)*Parametros!$B$10,0) | N11: =IF(K11>6000000,ROUND((K11-6000000)*0.1,0),0) | O11: =Novedades_Horas!J11 | P11: =SUM(L11:O11) | Q11: =K11-P11 | R11: =ROUND(K11+(G11+I11+J11)*0.205,0) | S11: =IF(Q11<0,"ERROR: Neto negativo",IF(E11<Parametros!$B$5,"ERROR: Salario bajo",IF(E11>Parametros!$B$11,"REVISAR: salario alto","OK")))
A12: =Empleados!A12 | B12: =Empleados!B12 | C12: =Empleados!C12 | D12: =Empleados!D12 | E12: =Empleados!E12 | F12: =E12/Parametros!$B$8 | G12: =ROUND(E12/Parametros!$B$8*Novedades_Horas!C12,0) | H12: =IF(AND(E12<=Parametros!$B$7,Empleados!L12="Si"),Parametros!$B$6,0) | I12: =ROUND(F12*(Novedades_Horas!D12*Parametros!$B$12+Novedades_Horas!E12*Parametros!$B$13+Novedades_Horas!F12*Parametros!$B$14+Novedades_Horas!G12*Parametros!$B$15),0) | J12: =Novedades_Horas!I12 | K12: =SUM(G12:J12) | L12: =ROUND((G12+I12+J12)*Parametros!$B$9,0) | M12: =ROUND((G12+I12+J12)*Parametros!$B$10,0) | N12: =IF(K12>6000000,ROUND((K12-6000000)*0.1,0),0) | O12: =Novedades_Horas!J12 | P12: =SUM(L12:O12) | Q12: =K12-P12 | R12: =ROUND(K12+(G12+I12+J12)*0.205,0) | S12: =IF(Q12<0,"ERROR: Neto negativo",IF(E12<Parametros!$B$5,"ERROR: Salario bajo",IF(E12>Parametros!$B$11,"REVISAR: salario alto","OK")))
A13: =Empleados!A13 | B13: =Empleados!B13 | C13: =Empleados!C13 | D13: =Empleados!D13 | E13: =Empleados!E13 | F13: =E13/Parametros!$B$8 | G13: =ROUND(E13/Parametros!$B$8*Novedades_Horas!C13,0) | H13: =IF(AND(E13<=Parametros!$B$7,Empleados!L13="Si"),Parametros!$B$6,0) | I13: =ROUND(F13*(Novedades_Horas!D13*Parametros!$B$12+Novedades_Horas!E13*Parametros!$B$13+Novedades_Horas!F13*Parametros!$B$14+Novedades_Horas!G13*Parametros!$B$15),0) | J13: =Novedades_Horas!I13 | K13: =SUM(G13:J13) | L13: =ROUND((G13+I13+J13)*Parametros!$B$9,0) | M13: =ROUND((G13+I13+J13)*Parametros!$B$10,0) | N13: =IF(K13>6000000,ROUND((K13-6000000)*0.1,0),0) | O13: =Novedades_Horas!J13 | P13: =SUM(L13:O13) | Q13: =K13-P13 | R13: =ROUND(K13+(G13+I13+J13)*0.205,0) | S13: =IF(Q13<0,"ERROR: Neto negativo",IF(E13<Parametros!$B$5,"ERROR: Salario bajo",IF(E13>Parametros!$B$11,"REVISAR: salario alto","OK")))
... A31: =Empleados!A31 | B31: =Empleados!B31 | C31: =Empleados!C31 | D31: =Empleados!D31 | E31: =Empleados!E31 | F31: =E31/Parametros!$B$8 | G31: =ROUND(E31/Parametros!$B$8*Novedades_Horas!C31,0) | H31: =IF(AND(E31<=Parametros!$B$7,Empleados!L31="Si"),Parametros!$B$6,0) | I31: =ROUND(F31*(Novedades_Horas!D31*Parametros!$B$12+Novedades_Horas!E31*Parametros!$B$13+Novedades_Horas!F31*Parametros!$B$14+Novedades_Horas!G31*Parametros!$B$15),0) | J31: =Novedades_Horas!I31 | K31: =SUM(G31:J31) | L31: =ROUND((G31+I31+J31)*Parametros!$B$9,0) | M31: =ROUND((G31+I31+J31)*Parametros!$B$10,0) | N31: =IF(K31>6000000,ROUND((K31-6000000)*0.1,0),0) | O31: =Novedades_Horas!J31 | P31: =SUM(L31:O31) | Q31: =K31-P31 | R31: =ROUND(K31+(G31+I31+J31)*0.205,0) | S31: =IF(Q31<0,"ERROR: Neto negativo",IF(E31<Parametros!$B$5,"ERROR: Salario bajo",IF(E31>Parametros!$B$11,"REVISAR: salario alto","OK")))

Sheet Validaciones
A1: Regla | B1: Resultado | C1: Accion sugerida
A2: Empleados sin nombre | B2: =COUNTBLANK(Empleados!B2:B500) | C2: Completar nombre o eliminar registro vacio
A3: Salarios por debajo de SMLMV | B3: =COUNTIF(Empleados!E2:E500,"<"&Parametros!$B$5) | C3: Ajustar salario base a minimo legal o justificar excepcion
A4: Horas ordinarias fuera de rango | B4: =COUNTIFS(Novedades_Horas!C2:C500,">240")+COUNTIFS(Novedades_Horas!C2:C500,"<0") | C4: Revisar horas ordinarias del periodo
A5: Netos negativos | B5: =COUNTIF(Calculo_Nomina!Q2:Q500,"<0") | C5: Revisar deducciones, prestamos o novedades
A6: Registros marcados por agente | B6: =COUNTIF(Calculo_Nomina!S2:S500,"<>OK") | C6: Filtrar EstadoAgente en Calculo_Nomina

Sheet Reporte_Gerencial
A1: Resumen de nomina
D2: Costo por area
A3: Periodo | B3: =DATE(Parametros!$B$2,Parametros!$B$3,1) | D3: Area | E3: Neto a pagar | F3: Costo estimado
A4: Empleados activos | B4: =COUNTIF(Empleados!L:L,"Si") | D4: Administracion | E4: =SUMIF(Calculo_Nomina!D:D,D4,Calculo_Nomina!Q:Q) | F4: =SUMIF(Calculo_Nomina!D:D,D4,Calculo_Nomina!R:R)
A5: Total devengado | B5: =SUM(Calculo_Nomina!K:K) | D5: Comercial | E5: =SUMIF(Calculo_Nomina!D:D,D5,Calculo_Nomina!Q:Q) | F5: =SUMIF(Calculo_Nomina!D:D,D5,Calculo_Nomina!R:R)
A6: Total deducciones | B6: =SUM(Calculo_Nomina!P:P) | D6: Finanzas | E6: =SUMIF(Calculo_Nomina!D:D,D6,Calculo_Nomina!Q:Q) | F6: =SUMIF(Calculo_Nomina!D:D,D6,Calculo_Nomina!R:R)
A7: Total neto a pagar | B7: =SUM(Calculo_Nomina!Q:Q) | D7: Operaciones | E7: =SUMIF(Calculo_Nomina!D:D,D7,Calculo_Nomina!Q:Q) | F7: =SUMIF(Calculo_Nomina!D:D,D7,Calculo_Nomina!R:R)
A8: Costo empresa estimado | B8: =SUM(Calculo_Nomina!R:R) | D8: Talento Humano | E8: =SUMIF(Calculo_Nomina!D:D,D8,Calculo_Nomina!Q:Q) | F8: =SUMIF(Calculo_Nomina!D:D,D8,Calculo_Nomina!R:R)
A9: Alertas abiertas | B9: =COUNTIF(Calculo_Nomina!S:S,"<>OK")-1 | D9: Tecnologia | E9: =SUMIF(Calculo_Nomina!D:D,D9,Calculo_Nomina!Q:Q) | F9: =SUMIF(Calculo_Nomina!D:D,D9,Calculo_Nomina!R:R)

Sheet Escenarios
A1: Escenario | B1: Parametro | C1: Valor | D1: Resultado estimado | E1: Formula/accion
A2: Base actual | B2: Aumento salarial | C2: 0 | D2: =SUM(Calculo_Nomina!Q:Q) | E2: Neto a pagar actual
A3: Simular aumento 10% | B3: Aumento salarial | C3: 0.1 | D3: =ROUND(SUM(Calculo_Nomina!Q:Q)*(1+C3),0) | E3: Impacto aproximado sobre neto
A4: Agregar 5 empleados minimo | B4: Cantidad | C4: 5 | D4: =C4*Parametros!$B$5 | E4: Costo salarial base antes de aportes
A5: Sin auxilio transporte | B5: Auxilio | C5: 0 | D5: =SUM(Calculo_Nomina!Q:Q)-SUM(Calculo_Nomina!H:H) | E5: Comparativo sin auxilio

Sheet Agente_NL
A1: Interfaz inteligente: comandos soportados
A2: Comando natural | B2: Como se ejecuta en el libro | C2: Estado
A3: Agrega 5 empleados con salario minimo | B3: Duplicar 5 filas base en Empleados con SalarioBase = Parametros!SMLMV y crear sus novedades | C3: Plantilla lista
A4: Calcula nomina del mes | B4: Editar Parametros Mes/Anio; Excel recalcula Calculo_Nomina y Reporte_Gerencial | C4: Automatico
A5: Simula aumento del 10% | B5: Usar fila Simular aumento 10% en Escenarios o cambiar C3 | C5: Automatico
A6: Revisa errores | B6: Abrir Validaciones y filtrar EstadoAgente en Calculo_Nomina | C6: Automatico
A7: Genera reporte de fin de mes | B7: Reporte_Gerencial consolida totales, costos por area y graficos | C7: Automatico
A10: Nota operativa
A11: Este archivo usa formulas, tablas, validaciones y recalculo al abrir. Para eventos 100% activos tipo macro, se puede migrar a .xlsm u Office Scripts sobre esta misma estructura.

Sheet Bitacora_Workflows
A1: Workflow | B1: Disparador | C1: Accion automatizada | D1: Implementacion actual
A2: Alta empleado | B2: Nueva fila en Empleados | C2: Generar registro completo y novedades | D2: Tabla estructurada + validaciones + plantilla en Agente_NL
A3: Cambio salario | B3: Cambio en SalarioBase | C3: Recalcular devengado, deducciones, neto y alertas | D3: Formulas enlazadas con recalculo automatico
A4: Fin de mes | B4: Cambio Mes/Anio o cierre periodo | C4: Actualizar resumen y graficos | D4: Reporte_Gerencial con formulas y graficos
A5: Control errores | B5: Datos fuera de rango | C5: Marcar errores y sugerir correccion | D5: Validaciones + EstadoAgente + formato condicional
A6: Simulacion | B6: Cambio de escenario | C6: Estimar impacto financiero | D6: Hoja Escenarios
